README.md
setup.py
Rocket/Rocket.py
Rocket/__init__.py
Rocket_rocket_rocket_rocket.egg-info/PKG-INFO
Rocket_rocket_rocket_rocket.egg-info/SOURCES.txt
Rocket_rocket_rocket_rocket.egg-info/dependency_links.txt
Rocket_rocket_rocket_rocket.egg-info/top_level.txt