Metadata-Version: 2.4
Name: Rocket_rocket_rocket_rocket
Version: 1.0.0
Summary: An awesome package that does something
Home-page: http://pypi.python.org/pypi/Rocket_rocket_rocket_rocket/
Author: mohamed23333444
Author-email: mohmooh33@gmail.com
License: LICENSE.txt
Dynamic: author
Dynamic: author-email
Dynamic: description
Dynamic: description-content-type
Dynamic: home-page
Dynamic: license
Dynamic: summary
